azbacklog/__init__.py
azbacklog/azbacklog.py
azbacklog/entities/__init__.py
azbacklog/entities/epic.py
azbacklog/entities/feature.py
azbacklog/entities/tag.py
azbacklog/entities/task.py
azbacklog/entities/userstory.py
azbacklog/helpers/__init__.py
azbacklog/helpers/actions.py
azbacklog/helpers/backlog.py
azbacklog/helpers/filesystem.py
azbacklog/helpers/parser.py
azbacklog/helpers/validation.py
azbacklog/services/__init__.py
azbacklog/services/azure.py
azbacklog/services/github.py
azbacklog-1.0.2.data/data/workitems/caf/README.md
azbacklog-1.0.2.data/data/workitems/caf/config.json
azbacklog-1.0.2.data/data/workitems/caf/01_CloudAdoptionStrategy/metadata.json
azbacklog-1.0.2.data/data/workitems/caf/01_CloudAdoptionStrategy/01_DefineAdoptionStrategy/metadata.json
azbacklog-1.0.2.data/data/workitems/caf/01_CloudAdoptionStrategy/01_DefineAdoptionStrategy/01_Motivations/metadata.json
azbacklog-1.0.2.data/data/workitems/caf/01_CloudAdoptionStrategy/01_DefineAdoptionStrategy/02_BusinessOutcomes/metadata.json
azbacklog-1.0.2.data/data/workitems/caf/01_CloudAdoptionStrategy/01_DefineAdoptionStrategy/03_BusinessCase/metadata.json
azbacklog-1.0.2.data/data/workitems/caf/01_CloudAdoptionStrategy/01_DefineAdoptionStrategy/04_FirstAdoptionProject/metadata.json
azbacklog-1.0.2.data/data/workitems/caf/02_CloudAdoptionPlan/metadata.json
azbacklog-1.0.2.data/data/workitems/caf/02_CloudAdoptionPlan/01_DefineTheCloudAdoptionPlan/metadata.json
azbacklog-1.0.2.data/data/workitems/caf/02_CloudAdoptionPlan/01_DefineTheCloudAdoptionPlan/01_DigitalEstate/metadata.json
azbacklog-1.0.2.data/data/workitems/caf/02_CloudAdoptionPlan/01_DefineTheCloudAdoptionPlan/02_InitialOrganizationalAlignment/metadata.json
azbacklog-1.0.2.data/data/workitems/caf/02_CloudAdoptionPlan/01_DefineTheCloudAdoptionPlan/03_SkillsReadinessPlan/metadata.json
azbacklog-1.0.2.data/data/workitems/caf/02_CloudAdoptionPlan/01_DefineTheCloudAdoptionPlan/04_UpdateThisCloudAdoptionPlan/metadata.json
azbacklog-1.0.2.dist-info/LICENSE
azbacklog-1.0.2.dist-info/METADATA
azbacklog-1.0.2.dist-info/WHEEL
azbacklog-1.0.2.dist-info/entry_points.txt
azbacklog-1.0.2.dist-info/top_level.txt
azbacklog-1.0.2.dist-info/RECORD
