Metadata-Version: 2.1
Name: azbacklog
Version: 1.0.2
Summary: The Azure Backlog Generator (ABG) is designed to build backlogs for complex processes based on proven practices. The backlogs can be generated in either Azure DevOps or GitHub.
Home-page: https://github.com/Azure/Azure-Backlog-Generator
Author: Joshua Davis
Author-email: me@jdav.is
License: UNKNOWN
Platform: UNKNOWN
Requires-Python: >=3.6
Requires-Dist: pygithub (==1.51)
Requires-Dist: azure-devops (==6.0.0b2)
Provides-Extra: dev
Requires-Dist: pyfakefs ; extra == 'dev'
Requires-Dist: pytest ; extra == 'dev'
Requires-Dist: coverage ; extra == 'dev'
Requires-Dist: mock ; extra == 'dev'
Requires-Dist: flake8 ; extra == 'dev'
